semanticsdp/__init__.py
semanticsdp/_base.py
semanticsdp/_dataclass_fix.py
semanticsdp/candidate_info.py
semanticsdp/codec_info.py
semanticsdp/crypto_info.py
semanticsdp/datachannel_info.py
semanticsdp/direction.py
semanticsdp/direction_way.py
semanticsdp/dtls_info.py
semanticsdp/ice_info.py
semanticsdp/media_info.py
semanticsdp/rid_info.py
semanticsdp/rtcp_feedback_info.py
semanticsdp/sdp_info.py
semanticsdp/setup.py
semanticsdp/simulcast_info.py
semanticsdp/simulcast_stream_info.py
semanticsdp/source_group_info.py
semanticsdp/source_info.py
semanticsdp/stream_info.py
semanticsdp/track_encoding_info.py
semanticsdp/track_info.py
semanticsdp/transform/__init__.py
semanticsdp/transform/sdp_grammar.py
semanticsdp/transform/sdp_parser.py
semanticsdp/transform/sdp_writer.py
semanticsdp-0.1.0b9.dist-info/LICENSE
semanticsdp-0.1.0b9.dist-info/METADATA
semanticsdp-0.1.0b9.dist-info/WHEEL
semanticsdp-0.1.0b9.dist-info/RECORD
