Metadata-Version: 2.1
Name: semanticsdp
Version: 0.1.0b9
Summary: Python port of medooze/semantic-sdp-js
Author: RuslanUC
Author-email: dev_ruslan_uc@protonmail.com
Requires-Python: >=3.9,<4.0
Classifier: Programming Language :: Python :: 3
Classifier: Programming Language :: Python :: 3.9
Classifier: Programming Language :: Python :: 3.10
Classifier: Programming Language :: Python :: 3.11
